an_kohyasetupmanager/__init__.py
an_kohyasetupmanager/kohyasetupmanager.py
an_kohyasetupmanager-1.0.1.dist-info/licenses/LICENSE
an_kohyasetupmanager-1.0.1.dist-info/METADATA
an_kohyasetupmanager-1.0.1.dist-info/WHEEL
an_kohyasetupmanager-1.0.1.dist-info/top_level.txt
an_kohyasetupmanager-1.0.1.dist-info/RECORD
