Metadata-Version: 2.4
Name: an_kohyasetupmanager
Version: 1.0.1
Summary: A package for an_kohyasetupmanager.
Home-page: https://github.com/Atsushi888/Atsushi888
Author: Atsushi888
Author-email: Atsushi888 <vtgrotxu@gmail.com>
Project-URL: Homepage, https://github.com/Atsushi888/an_kohyasetupmanager
Project-URL: Repository, https://github.com/Atsushi888/an_kohyasetupmanager
Requires-Python: >=3.6
License-File: LICENSE
Requires-Dist: an_DebugHelper>=1.3.3
Requires-Dist: an_CudaUtility
Requires-Dist: an_CondaManager
Requires-Dist: an_EasyVen
Requires-Dist: an_ToolKit
Dynamic: author
Dynamic: home-page
Dynamic: license-file
Dynamic: requires-python
